{
	"name": "level7",
	"layers": [
		{
			"name": "Space",
			"overriden": 0,
			"subLayers": [],
			"instances": [
				{
					"type": "Space",
					"properties": {
						"initially-visible": true,
						"origin": "top-left",
						"wrap-horizontal": "repeat",
						"wrap-vertical": "repeat",
						"image-offset-x": 0,
						"image-offset-y": 0,
						"image-scale-x": 1,
						"image-scale-y": 1,
						"image-angle": 0,
						"enable-tile-randomization": false,
						"x-random": 1,
						"y-random": 1,
						"angle-random": 1,
						"blend-margin-x": 0.1,
						"blend-margin-y": 0.1
					},
					"uid": 30,
					"instanceVariables": {},
					"behaviors": {},
					"world": {
						"x": 0,
						"y": 0,
						"width": 1712,
						"height": 960,
						"originX": 0,
						"originY": 0,
						"color": [
							1,
							1,
							1,
							1
						],
						"angle": 0,
						"zElevation": 0
					}
				}
			],
			"sid": 820780790255832,
			"effectTypes": [],
			"isInitiallyVisible": true,
			"isInitiallyInteractive": true,
			"color": [
				1,
				1,
				1,
				1
			],
			"backgroundColor": [
				0.3686274509803922,
				0.3686274509803922,
				0.3686274509803922,
				1
			],
			"isTransparent": false,
			"parallaxX": 1,
			"parallaxY": 1,
			"scaleRate": 1,
			"forceOwnTexture": false,
			"renderingMode": "3d",
			"drawOrder": "z-order",
			"useRenderCells": false,
			"blendMode": "normal",
			"zElevation": 0,
			"global": false
		},
		{
			"name": "Back",
			"overriden": 0,
			"subLayers": [],
			"instances": [
				{
					"type": "BackTile",
					"properties": {
						"initially-visible": true,
						"tile-width": 16,
						"tile-height": 16,
						"tile-x-offset": 0,
						"tile-y-offset": 0,
						"tile-x-spacing": 0,
						"tile-y-spacing": 0,
						"tile-x-drawing-offset": 0,
						"tile-y-drawing-offset": 0,
						"drawing-mode": "top-to-right"
					},
					"uid": 31,
					"instanceVariables": {},
					"behaviors": {},
					"ownData": {
						"tilemapData": {
							"width": 106,
							"height": 60,
							"max-width": 106,
							"max-height": 60,
							"data": "244x0,12x9hv,28x0,11x9hv,9x0,12x9hv,28x0,11x9hv,9x0,51x9hv,9x0,51x9hv,9x0,51x9hv,9x0,51x9hv,9x0,51x9hv,9x0,51x9hv,9x0,51x9hv,9x0,51x9hv,9x0,12x9hv,28x0,11x9hv,9x0,12x9hv,28x0,11x9hv,11x0,8x9hv,30x0,11x9hv,11x0,8x9hv,30x0,11x9hv,11x0,8x9hv,30x0,11x9hv,11x0,8x9hv,30x0,11x9hv,11x0,8x9hv,30x0,11x9hv,11x0,8x9hv,30x0,11x9hv,11x0,8x9hv,30x0,11x9hv,11x0,8x9hv,30x0,11x9hv,11x0,8x9hv,30x0,11x9hv,11x0,8x9hv,30x0,11x9hv,11x0,8x9hv,30x0,11x9hv,11x0,8x9hv,30x0,11x9hv,11x0,8x9hv,30x0,11x9hv,11x0,8x9hv,30x0,11x9hv,11x0,8x9hv,30x0,11x9hv,11x0,8x9hv,30x0,11x9hv,11x0,8x9hv,30x0,11x9hv,11x0,8x9hv,30x0,11x9hv,11x0,8x9hv,30x0,11x9hv,11x0,8x9hv,30x0,11x9hv,11x0,8x9hv,30x0,11x9hv,11x0,8x9hv,30x0,11x9hv,11x0,8x9hv,30x0,11x9hv,11x0,8x9hv,30x0,11x9hv,11x0,8x9hv,30x0,9x9hv,13x0,8x9hv,30x0,9x9hv,13x0,9x9hv,18x0,22x9hv,11x0,9x9hv,18x0,22x9hv,11x0,9x9hv,18x0,22x9hv,11x0,9x9hv,18x0,22x9hv,11x0,9x9hv,18x0,22x9hv,11x0,9x9hv,18x0,22x9hv,11x0,9x9hv,18x0,22x9hv,11x0,9x9hv,18x0,22x9hv,11x0,9x9hv,18x0,22x9hv,11x0,9x9hv,18x0,22x9hv,11x0,9x9hv,18x0,22x9hv,11x0,9x9hv,18x0,22x9hv,11x0,14x9hv,13x0,22x9hv,8x0,17x9hv,13x0,22x9hv,8x0,17x9hv,13x0,22x9hv,8x0,17x9hv,13x0,22x9hv,8x0,17x9hv,13x0,22x9hv,8x0,17x9hv,13x0,22x9hv,8x0,17x9hv,13x0,22x9hv,8x0,17x9hv,13x0,22x9hv,8x0,17x9hv,13x0,22x9hv,8x0,17x9hv,13x0,22x9hv,8x0,17x9hv,13x0,22x9hv,8x0,17x9hv,13x0,22x9hv,8x0,17x9hv,13x14hv,22x9hv,8x0,17x9hv,13x14hv,22x9hv,8x0,17x9hv,13x14hv,22x9hv,8x0,17x9hv,13x14hv,22x9hv,8x0,17x9hv,13x14hv,22x9hv,8x0,17x9hv,13x14hv,22x9hv,8x0,17x9hv,13x14hv,22x9hv,8x0,17x9hv,13x14hv,22x9hv,8x0,52x9hv,8x0,17x9hv,13x0,22x9hv,8x0,17x9hv,13x0,22x9hv,8x0,17x9hv,13x0,22x9hv,8x0,17x9hv,13x0,22x9hv,8x0,17x9hv,13x0,22x9hv,8x0,17x9hv,13x0,22x9hv,8x0,17x9hv,13x0,22x9hv,8x0,17x9hv,13x0,22x9hv,8x0,17x9hv,13x0,22x9hv,8x0,17x9hv,47x0,7x14hv,53x0,7x14hv,53x0,7x14hv,53x0,7x14hv,53x0,7x14hv,53x0,7x14hv,53x0,7x14hv,53x0,7x14hv,53x0,7x14hv,766x0"
						},
						"tile-width": 16,
						"tile-height": 16,
						"tile-x-offset": 0,
						"tile-y-offset": 0,
						"tile-x-spacing": 0,
						"tile-y-spacing": 0
					},
					"world": {
						"x": 0,
						"y": 0,
						"width": 1708,
						"height": 960,
						"originX": 0,
						"originY": 0,
						"color": [
							1,
							1,
							1,
							1
						],
						"zElevation": 0
					}
				}
			],
			"sid": 191907777260469,
			"effectTypes": [],
			"isInitiallyVisible": true,
			"isInitiallyInteractive": true,
			"color": [
				1,
				1,
				1,
				1
			],
			"backgroundColor": [
				0.3686274509803922,
				0.3686274509803922,
				0.3686274509803922,
				1
			],
			"isTransparent": true,
			"parallaxX": 1,
			"parallaxY": 1,
			"scaleRate": 1,
			"forceOwnTexture": false,
			"renderingMode": "3d",
			"drawOrder": "z-order",
			"useRenderCells": false,
			"blendMode": "normal",
			"zElevation": 0,
			"global": false
		},
		{
			"name": "Walls",
			"overriden": 0,
			"subLayers": [],
			"instances": [
				{
					"type": "WallTile",
					"properties": {
						"initially-visible": true,
						"tile-width": 16,
						"tile-height": 16,
						"tile-x-offset": 0,
						"tile-y-offset": 0,
						"tile-x-spacing": 0,
						"tile-y-spacing": 0,
						"tile-x-drawing-offset": 0,
						"tile-y-drawing-offset": 0,
						"drawing-mode": "top-to-right"
					},
					"uid": 32,
					"instanceVariables": {},
					"behaviors": {},
					"ownData": {
						"tilemapData": {
							"width": 106,
							"height": 60,
							"max-width": 106,
							"max-height": 60,
							"data": "122x0,16x10,24x0,15x10,5x0,16x10,24x0,15x10,5x0,10,4,12x0,28x10,11x0,2x10,5x0,10,4,12x0,10,12x4,15x10,11x0,2x10,5x0,10,4,51x0,2x10,5x0,10,4,51x0,4,10,5x0,2x10,51x0,4,10,5x0,2x10,51x0,4,10,5x0,2x10,51x0,4,10,5x0,2x10,51x0,4,10,5x0,2x10,51x0,4,10,5x0,2x10,51x0,4,10,5x0,2x10,12x0,17x10,9x4,2x10,11x0,4,10,5x0,2x10,12x0,28x10,11x0,4,10,5x0,4x10,8x0,4x10,24x0,2x10,11x0,4,10,5x0,4x10,8x0,4x10,24x0,2x10,11x0,4,10,7x0,2x10,8x0,2x10,26x0,2x10,11x0,4,10,7x0,2x10,8x0,2x10,26x0,2x10,11x0,4,10,7x0,2x10,8x0,2x10,26x0,2x10,11x0,4,10,7x0,2x10,8x0,2x10,26x0,2x10,11x0,2x10,7x0,2x10,8x0,2x10,26x0,2x10,11x0,2x10,7x0,2x10,8x0,2x10,26x0,2x10,11x0,2x10,7x0,2x10,8x0,2x10,26x0,2x10,11x0,2x10,7x0,2x10,8x0,2x10,26x0,2x10,11x0,2x10,7x0,2x10,8x0,2x10,26x0,2x10,11x0,2x10,7x0,2x10,8x0,4,10,26x0,2x10,11x0,2x10,7x0,2x10,8x0,4,10,26x0,2x10,11x0,2x10,7x0,2x10,8x0,4,10,26x0,2x10,11x0,2x10,7x0,2x10,8x0,4,10,26x0,2x10,11x0,2x10,7x0,2x10,8x0,4,10,26x0,2x10,11x0,2x10,7x0,2x10,8x0,4,10,26x0,2x10,11x0,2x10,7x0,2x10,8x0,4,10,26x0,2x10,11x0,2x10,7x0,2x10,8x0,4,10,26x0,2x10,11x0,2x10,7x0,2x10,8x0,4,10,26x0,2x10,11x0,2x10,7x0,2x10,8x0,4,10,26x0,2x10,11x0,2x10,7x0,2x10,8x0,4,10,26x0,2x10,11x0,2x10,7x0,2x10,8x0,4,10,26x0,2x10,11x0,2x10,7x0,2x10,8x0,4,10,26x0,2x10,11x0,2x10,7x0,10,4,8x0,4,10,15x0,13x10,9x0,4x10,7x0,10,4,8x0,4,10,15x0,13x10,9x0,4x10,7x0,10,4,8x0,4,10,15x0,2x10,22x0,2x10,7x0,10,4,8x0,2x10,15x0,2x10,22x0,4,10,7x0,10,4,8x0,2x10,15x0,2x10,22x0,4,10,7x0,10,4,8x0,2x10,15x0,2x10,22x0,4,10,7x0,10,4,8x0,2x10,15x0,2x10,22x0,4,10,7x0,10,4,8x0,2x10,15x0,2x10,22x0,4,10,7x0,10,4,8x0,2x10,15x0,2x10,22x0,4,10,7x0,10,4,8x0,2x10,15x0,2x10,22x0,4,10,7x0,2x10,8x0,2x10,15x0,2x10,22x0,4,10,7x0,2x10,8x0,2x10,15x0,2x10,22x0,4,10,7x0,2x10,8x0,8x10,9x0,2x10,22x0,4,10,4x0,5x10,8x0,8x10,9x0,2x10,22x0,4,10,4x0,5x10,14x0,2x10,9x0,2x10,22x0,4,10,4x0,2x10,17x0,2x10,9x0,2x10,22x0,4,10,4x0,2x10,17x0,2x10,9x0,2x10,22x0,4,10,4x0,2x10,17x0,2x10,9x0,2x10,22x0,4,10,4x0,2x10,17x0,12,10,9x0,10,12hv,22x0,12,10,4x0,2x10,17x0,12,10,9x0,10,12hv,22x0,12,10,4x0,2x10,17x0,12,10,9x0,10,12hv,22x0,12,10,4x0,2x10,17x0,12,10,9x0,10,12hv,22x0,12,10,4x0,2x10,17x0,12,10,9x0,10,12hv,22x0,12,10,4x0,2x10,17x0,12,10,9x0,10,12hv,22x0,12,10,4x0,2x10,17x0,12,10,9x0,10,12hv,22x0,12,10,4x0,2x10,17x0,13x4,22x0,12,10,4x0,2x10,52x0,12,10,4x0,2x10,52x0,12,10,4x0,2x10,52x0,2x10,4x0,2x10,52x0,2x10,4x0,2x10,52x0,2x10,4x0,2x10,52x0,2x10,4x0,2x10,52x0,2x10,4x0,2x10,52x0,2x10,4x0,2x10,17x0,13x4,22x0,2x10,4x0,2x10,17x0,12,10,9x0,10,12hv,22x0,2x10,4x0,2x10,17x0,12,10,9x0,10,12hv,22x0,2x10,4x0,2x10,17x0,12,10,9x0,10,12hv,22x0,2x10,4x0,2x10,17x0,12,10,9x0,10,12hv,22x0,2x10,4x0,2x10,17x0,12,10,9x0,10,12hv,22x0,2x10,4x0,2x10,17x0,12,10,9x0,10,12hv,22x0,2x10,4x0,2x10,17x0,12,10,9x0,2x10,22x0,2x10,4x0,2x10,17x0,12,10,9x0,2x10,22x0,2x10,4x0,2x10,17x0,2x10,9x0,2x10,22x0,2x10,4x0,2x10,17x0,2x10,9x0,10x10,10x4,6x10,4x0,5x10,8hv,7x0,8hv,7x10,9x0,26x10,4x0,5x10,8hv,7x0,8hv,7x10,44x0,12,7x0,12hv,51x0,12,7x0,12hv,51x0,12,7x0,12hv,51x0,12,7x0,12hv,51x0,12,7x0,12hv,51x0,12,7x0,12hv,51x0,12,7x0,12hv,765x0"
						},
						"tile-width": 16,
						"tile-height": 16,
						"tile-x-offset": 0,
						"tile-y-offset": 0,
						"tile-x-spacing": 0,
						"tile-y-spacing": 0
					},
					"world": {
						"x": 0,
						"y": 0,
						"width": 1708,
						"height": 960,
						"originX": 0,
						"originY": 0,
						"color": [
							1,
							1,
							1,
							1
						],
						"zElevation": 0
					}
				}
			],
			"sid": 622170376460542,
			"effectTypes": [],
			"isInitiallyVisible": true,
			"isInitiallyInteractive": true,
			"color": [
				1,
				1,
				1,
				1
			],
			"backgroundColor": [
				0.3686274509803922,
				0.3686274509803922,
				0.3686274509803922,
				1
			],
			"isTransparent": true,
			"parallaxX": 1,
			"parallaxY": 1,
			"scaleRate": 1,
			"forceOwnTexture": false,
			"renderingMode": "3d",
			"drawOrder": "z-order",
			"useRenderCells": false,
			"blendMode": "normal",
			"zElevation": 0,
			"global": false
		},
		{
			"name": "Ships",
			"overriden": 0,
			"subLayers": [],
			"instances": [],
			"sid": 987364473988776,
			"effectTypes": [],
			"isInitiallyVisible": true,
			"isInitiallyInteractive": true,
			"color": [
				1,
				1,
				1,
				1
			],
			"backgroundColor": [
				0.3686274509803922,
				0.3686274509803922,
				0.3686274509803922,
				1
			],
			"isTransparent": true,
			"parallaxX": 1,
			"parallaxY": 1,
			"scaleRate": 1,
			"forceOwnTexture": false,
			"renderingMode": "3d",
			"drawOrder": "z-order",
			"useRenderCells": false,
			"blendMode": "normal",
			"zElevation": 0,
			"global": false
		},
		{
			"name": "Objects",
			"overriden": 0,
			"subLayers": [],
			"instances": [],
			"sid": 661197027295161,
			"effectTypes": [],
			"isInitiallyVisible": true,
			"isInitiallyInteractive": true,
			"color": [
				1,
				1,
				1,
				1
			],
			"backgroundColor": [
				0.3686274509803922,
				0.3686274509803922,
				0.3686274509803922,
				1
			],
			"isTransparent": true,
			"parallaxX": 1,
			"parallaxY": 1,
			"scaleRate": 1,
			"forceOwnTexture": false,
			"renderingMode": "3d",
			"drawOrder": "z-order",
			"useRenderCells": false,
			"blendMode": "normal",
			"zElevation": 0,
			"global": false
		},
		{
			"name": "Bullets",
			"overriden": 0,
			"subLayers": [],
			"instances": [],
			"sid": 258250354562333,
			"effectTypes": [],
			"isInitiallyVisible": true,
			"isInitiallyInteractive": true,
			"color": [
				1,
				1,
				1,
				1
			],
			"backgroundColor": [
				0.3686274509803922,
				0.3686274509803922,
				0.3686274509803922,
				1
			],
			"isTransparent": true,
			"parallaxX": 1,
			"parallaxY": 1,
			"scaleRate": 1,
			"forceOwnTexture": false,
			"renderingMode": "3d",
			"drawOrder": "z-order",
			"useRenderCells": false,
			"blendMode": "normal",
			"zElevation": 0,
			"global": false
		},
		{
			"name": "Effects",
			"overriden": 0,
			"subLayers": [],
			"instances": [],
			"sid": 800502029009021,
			"effectTypes": [],
			"isInitiallyVisible": true,
			"isInitiallyInteractive": true,
			"color": [
				1,
				1,
				1,
				1
			],
			"backgroundColor": [
				0.3686274509803922,
				0.3686274509803922,
				0.3686274509803922,
				1
			],
			"isTransparent": true,
			"parallaxX": 1,
			"parallaxY": 1,
			"scaleRate": 1,
			"forceOwnTexture": false,
			"renderingMode": "3d",
			"drawOrder": "z-order",
			"useRenderCells": false,
			"blendMode": "normal",
			"zElevation": 0,
			"global": false
		},
		{
			"name": "Interface",
			"overriden": 0,
			"subLayers": [],
			"instances": [],
			"sid": 800203542964990,
			"effectTypes": [],
			"isInitiallyVisible": true,
			"isInitiallyInteractive": true,
			"color": [
				1,
				1,
				1,
				1
			],
			"backgroundColor": [
				0.3686274509803922,
				0.3686274509803922,
				0.3686274509803922,
				1
			],
			"isTransparent": true,
			"parallaxX": 1,
			"parallaxY": 1,
			"scaleRate": 1,
			"forceOwnTexture": false,
			"renderingMode": "3d",
			"drawOrder": "z-order",
			"useRenderCells": false,
			"blendMode": "normal",
			"zElevation": 0,
			"global": false
		}
	],
	"sid": 649161759279748,
	"nonworld-instances": [],
	"effectTypes": [],
	"width": 1708,
	"height": 960,
	"unboundedScrolling": false,
	"vpX": 0.5,
	"vpY": 0.5,
	"projection": "perspective",
	"eventSheet": "es_level_1"
}